.gitignore
MANIFEST.in
README.rst
deltacloud.py
python-deltacloud-client.spec
setup.py
deltacloud.egg-info/PKG-INFO
deltacloud.egg-info/SOURCES.txt
deltacloud.egg-info/dependency_links.txt
deltacloud.egg-info/requires.txt
deltacloud.egg-info/top_level.txt