Metadata-Version: 1.1
Name: deltacloud
Version: 0.9.1
Summary: Python client library for Deltacloud API
Home-page: http://deltacloud.apache.org/
Author: Tomas Sedovic
Author-email: tomas@sedovic.cz
License: UNKNOWN
Platform: UNKNOWN
Classifier: Programming Language :: Python
Classifier: Programming Language :: Python :: 3
Classifier: Development Status :: 4 - Beta
Classifier: Environment :: Other Environment
Classifier: Intended Audience :: Developers
Classifier: License :: OSI Approved :: Apache Software License
Classifier: Operating System :: OS Independent
Classifier: Topic :: Software Development :: Libraries :: Python Modules
